pyhasse.fuzzy-0.1.1-py3.7-nspkg.pth
pyhasse/fuzzy/__init__.py
pyhasse/fuzzy/calc.py
pyhasse.fuzzy-0.1.1.dist-info/AUTHORS.rst
pyhasse.fuzzy-0.1.1.dist-info/LICENSE
pyhasse.fuzzy-0.1.1.dist-info/LICENSE~
pyhasse.fuzzy-0.1.1.dist-info/METADATA
pyhasse.fuzzy-0.1.1.dist-info/WHEEL
pyhasse.fuzzy-0.1.1.dist-info/namespace_packages.txt
pyhasse.fuzzy-0.1.1.dist-info/top_level.txt
pyhasse.fuzzy-0.1.1.dist-info/RECORD
