Metadata-Version: 2.1
Name: pyhasse.fuzzy
Version: 0.1.1
Summary: pyhasse-fuzzy: Concept of De Walle et al […], where the relations between two objects are evaluated by fuzzy techniques.
Home-page: https://bitbucket.com/brg/fuzzy
Author: Rainer Bruggemann
Author-email: rainer.bruggemann@pyhasse.org
License: MIT license
Keywords: fuzzy
Platform: UNKNOWN
Classifier: Development Status :: 2 - Pre-Alpha
Classifier: Intended Audience :: Developers
Classifier: Topic :: Scientific/Engineering :: Mathematics
Classifier: License :: OSI Approved :: MIT License
Classifier: Natural Language :: English
Classifier: Programming Language :: Python :: 3.6
Classifier: Programming Language :: Python :: 3.7
Requires-Dist: setuptools
Requires-Dist: pyhasse.core
